README.md
setup.py
frasco_users/__init__.py
frasco_users/admin.py
frasco_users/blueprint.py
frasco_users/jinja_ext.py
frasco_users.egg-info/PKG-INFO
frasco_users.egg-info/SOURCES.txt
frasco_users.egg-info/dependency_links.txt
frasco_users.egg-info/not-zip-safe
frasco_users.egg-info/requires.txt
frasco_users.egg-info/top_level.txt
frasco_users/emails/users/reset_password.txt
frasco_users/emails/users/welcome.txt
frasco_users/templates/users/layout.html
frasco_users/templates/users/login.html
frasco_users/templates/users/reset_password.html
frasco_users/templates/users/send_reset_password.html
frasco_users/templates/users/signup.html