Metadata-Version: 1.0
Name: frasco-users
Version: 0.7.1
Summary: Users management for Frasco
Home-page: http://github.com/frascoweb/frasco-users
Author: Maxime Bouroumeau-Fuseau
Author-email: maxime.bouroumeau@gmail.com
License: MIT
Platform: any
